mwj_tools/__init__.py
mwj_tools/datetime_utils.py
mwj_tools/py.typed
mwj_tools/table_utils.py
mwj_tools-0.1.0.dist-info/WHEEL
mwj_tools-0.1.0.dist-info/METADATA
mwj_tools-0.1.0.dist-info/RECORD
