Metadata-Version: 2.3
Name: mwj-tools
Version: 0.1.0
Summary: 梦无矶的python工具库,不定时更新...
Author: mengwuji
Author-email: mengwuji <826199528@qq.com>
License: MIT
Requires-Dist: openpyxl>=3.1.5
Requires-Dist: pandas>=2.3.3
Requires-Dist: python-dateutil>=2.9.0.post0
Requires-Python: >=3.13
Project-URL: Homepage, https://github.com/Lvan826199/mwj_tools
Project-URL: Repository, https://github.com/Lvan826199/mwj_tools.git
